etc/ztpserver/ztpserver.conf
etc/ztpserver/ztpserver.wsgi
usr/share/ztpserver/neighbordb
usr/share/ztpserver/actions/add_config
usr/share/ztpserver/actions/configure_ansible_client
usr/share/ztpserver/actions/copy_file
usr/share/ztpserver/actions/install_cli_plugin
usr/share/ztpserver/actions/install_extension
usr/share/ztpserver/actions/install_image
usr/share/ztpserver/actions/replace_config
usr/share/ztpserver/actions/run_bash_script
usr/share/ztpserver/actions/run_cli_commands
usr/share/ztpserver/actions/send_email
usr/share/ztpserver/actions/template
usr/share/ztpserver/actions/the_nick
usr/share/ztpserver/bootstrap/bootstrap
usr/share/ztpserver/bootstrap/bootstrap.conf
usr/share/ztpserver/files/lib/requests-2.3.0.tar.gz
usr/share/ztpserver/plugins/allocate
usr/share/ztpserver/plugins/mysql_vars
usr/share/ztpserver/plugins/sqlite
usr/share/ztpserver/plugins/test
ztpserver/__init__.py
ztpserver/app.py
ztpserver/config.py
ztpserver/constants.py
ztpserver/controller.py
ztpserver/repository.py
ztpserver/resources.py
ztpserver/serializers.py
ztpserver/topology.py
ztpserver/types.py
ztpserver/utils.py
ztpserver/validators.py
ztpserver/wsgiapp.py
ztpserver-2.1.0.data/scripts/ztps
ztpserver-2.1.0.dist-info/LICENSE
ztpserver-2.1.0.dist-info/METADATA
ztpserver-2.1.0.dist-info/WHEEL
ztpserver-2.1.0.dist-info/top_level.txt
ztpserver-2.1.0.dist-info/RECORD
