Metadata-Version: 2.1
Name: ztpserver
Version: 2.1.0
Summary: ZTP Server for EOS
Home-page: https://github.com/arista-eosplus/ztpserver
Download-URL: https://github.com/arista-eosplus/ztpserver/tarball/v2.1.0
Author: Arista Networks
Author-email: eosplus-dev@arista.com
License: BSD-3
License-File: LICENSE
Requires-Dist: webob
Requires-Dist: routes
Requires-Dist: pyyaml
Requires-Dist: requests
